shortzy/__init__.py
shortzy/adlinkfly.py
shortzy/main.py
shortzy/shareus.py
shortzy/shareusio.py
shortzy-0.0.8.dist-info/LICENSE
shortzy-0.0.8.dist-info/METADATA
shortzy-0.0.8.dist-info/WHEEL
shortzy-0.0.8.dist-info/top_level.txt
shortzy-0.0.8.dist-info/RECORD
