Metadata-Version: 2.1
Name: shortzy
Version: 0.0.8
Summary: An Unofficial Asynchronous Python version of Adlinkfly and Alternative Website API wrapper
Home-page: https://github.com/kevinnadar22/shortzy
Author: Kevin Nadar
Author-email: jesikamaraj@gmail.com
License: MIT
Keywords: python,droplink,gplink,url-shortener,earn money,shareus,adlinkfly
Platform: UNKNOWN
Classifier: Development Status :: 2 - Pre-Alpha
Classifier: Intended Audience :: Developers
Classifier: Programming Language :: Python :: 3
Classifier: Operating System :: Unix
Classifier: Operating System :: MacOS :: MacOS X
Classifier: Operating System :: Microsoft :: Windows
License-File: LICENSE
